<?xml version="1.0"?>
<profile id="9">
    <firstname>foo</firstname>
    <lastname>bar</lastname>
    <email>foo@bar.net</email>
    <dob>1986</dob>
    <gender>0</gender>
    <phone>2104567890</phone>
    <smoker>0</smoker>
    <pet>0</pet>
    <child>0</child>
    <couple>1</couple>
    <we_are>2</we_are>
    <max_roommates>1</max_roommates>
    <visible>1</visible>
    <get_mail>0</get_mail>
    <token>7bda39fdf3c95f73587f16b710a83a1e30578133</token>
    <created>2011-11-10T10:58:46</created>
    <modified>2011-11-28T16:40:05</modified>
    <!--   <preference_id>9</preference_id> -->
    <!-- <user_id>11</user_id> -->
</profile>
